setup.py
yolapiAsync/__init__.py
yolapiAsync/yolapiAsync.py
yolapiAsync.egg-info/PKG-INFO
yolapiAsync.egg-info/SOURCES.txt
yolapiAsync.egg-info/dependency_links.txt
yolapiAsync.egg-info/requires.txt
yolapiAsync.egg-info/top_level.txt